docuforge/__init__.py
docuforge/callbacks.py
docuforge/chain.py
docuforge/cli.py
docuforge/components.py
docuforge/models.py
docuforge/prompts.py
docuforge-0.1.1.dist-info/licenses/LICENSE
docuforge-0.1.1.dist-info/METADATA
docuforge-0.1.1.dist-info/WHEEL
docuforge-0.1.1.dist-info/entry_points.txt
docuforge-0.1.1.dist-info/top_level.txt
docuforge-0.1.1.dist-info/RECORD
