Metadata-Version: 2.4
Name: docuforge
Version: 0.1.1
Summary: AI-powered content rewrite engine for PRD documents
Author: DocuForge Team
License: MIT
Project-URL: Homepage, https://github.com/ishowshao/DocuForge
Project-URL: Repository, https://github.com/ishowshao/DocuForge
Project-URL: Issues, https://github.com/ishowshao/DocuForge/issues
Keywords: ai,document,rewrite,prd,langchain
Classifier: Development Status :: 3 - Alpha
Classifier: Intended Audience :: Developers
Classifier: License :: OSI Approved :: MIT License
Classifier: Programming Language :: Python :: 3
Classifier: Programming Language :: Python :: 3.10
Classifier: Programming Language :: Python :: 3.11
Classifier: Programming Language :: Python :: 3.12
Requires-Python: >=3.10
License-File: LICENSE
Requires-Dist: annotated-types>=0.7.0
Requires-Dist: langchain>=0.3.25
Requires-Dist: langchain-core>=0.3.65
Requires-Dist: langchain-openai>=0.3.22
Requires-Dist: langgraph>=0.4.8
Requires-Dist: langgraph-checkpoint>=2.0.26
Requires-Dist: langsmith>=0.3.45
Requires-Dist: pydantic>=2.11.5
Requires-Dist: python-dotenv>=1.1.0
Requires-Dist: openai>=1.86.0
Requires-Dist: tenacity>=9.1.2
Provides-Extra: dev
Requires-Dist: pytest>=7.0.0; extra == "dev"
Requires-Dist: pytest-cov>=4.0.0; extra == "dev"
Requires-Dist: pytest-mock>=3.10.0; extra == "dev"
Requires-Dist: black>=23.0.0; extra == "dev"
Requires-Dist: isort>=5.12.0; extra == "dev"
Requires-Dist: mypy>=1.5.0; extra == "dev"
Requires-Dist: flake8>=6.0.0; extra == "dev"
Dynamic: license-file
